README.rst
setup.py
chainablemanager/__init__.py
chainablemanager/manager.py
chainablemanager/models.py
chainablemanager/tests.py
django_chainable_manager.egg-info/PKG-INFO
django_chainable_manager.egg-info/SOURCES.txt
django_chainable_manager.egg-info/dependency_links.txt
django_chainable_manager.egg-info/not-zip-safe
django_chainable_manager.egg-info/requires.txt
django_chainable_manager.egg-info/top_level.txt