Metadata-Version: 1.1
Name: django-chainable-manager
Version: 0.5.0
Summary: Chainable methods on Model managers
Home-page: https://bitbucket.org/tim_heap/django-chainable-manager
Author: Tim Heap
Author-email: tim@timheap.me
License: UNKNOWN
Platform: UNKNOWN
Classifier: Environment :: Web Environment
Classifier: Intended Audience :: Developers
Classifier: Operating System :: OS Independent
Classifier: Programming Language :: Python
Classifier: Framework :: Django
